pip_plant-0.3.4.data/scripts/pip-plant
plant/__init__.py
pip_plant-0.3.4.dist-info/LICENSE
pip_plant-0.3.4.dist-info/METADATA
pip_plant-0.3.4.dist-info/WHEEL
pip_plant-0.3.4.dist-info/top_level.txt
pip_plant-0.3.4.dist-info/RECORD
