Metadata-Version: 2.1
Name: pip-plant
Version: 0.3.4
Summary: Plant simplifies Python package management for projects.
Home-page: https://github.com/Ideas-Labs/plant
Author: Ideas Labs
Author-email: saurabh.chaturvedi63@gmail.com
License: MIT
Keywords: pip,packaging,python
Platform: UNKNOWN
Classifier: Intended Audience :: Developers
Classifier: Topic :: Software Development :: Build Tools
Classifier: License :: OSI Approved :: MIT License
Classifier: Programming Language :: Python :: 3
Requires-Dist: envoy
